onnion_runtime/__init__.py
onnion_runtime/abs.py
onnion_runtime/acos.py
onnion_runtime/acosh.py
onnion_runtime/add.py
onnion_runtime/and_.py
onnion_runtime/argmax.py
onnion_runtime/argmin.py
onnion_runtime/asin.py
onnion_runtime/asinh.py
onnion_runtime/atan.py
onnion_runtime/atanh.py
onnion_runtime/batchnormalization.py
onnion_runtime/bitshift.py
onnion_runtime/cast.py
onnion_runtime/ceil.py
onnion_runtime/celu.py
onnion_runtime/clip.py
onnion_runtime/compress.py
onnion_runtime/concat.py
onnion_runtime/concatfromsequence.py
onnion_runtime/constant.py
onnion_runtime/constantofshape.py
onnion_runtime/convtranspose.py
onnion_runtime/cos.py
onnion_runtime/cosh.py
onnion_runtime/depthtospace.py
onnion_runtime/dequantizelinear.py
onnion_runtime/det.py
onnion_runtime/div.py
onnion_runtime/dropout.py
onnion_runtime/dynamicquantizelinear.py
onnion_runtime/einsum.py
onnion_runtime/elu.py
onnion_runtime/equal.py
onnion_runtime/erf.py
onnion_runtime/error.py
onnion_runtime/exp.py
onnion_runtime/expand.py
onnion_runtime/eyelike.py
onnion_runtime/flatten.py
onnion_runtime/floor.py
onnion_runtime/gather.py
onnion_runtime/gatherelements.py
onnion_runtime/gathernd.py
onnion_runtime/gemm.py
onnion_runtime/globalaveragepool.py
onnion_runtime/globalmaxpool.py
onnion_runtime/greater.py
onnion_runtime/greaterorequal.py
onnion_runtime/hardmax.py
onnion_runtime/hardsigmoid.py
onnion_runtime/hardswish.py
onnion_runtime/identity.py
onnion_runtime/if_.py
onnion_runtime/instancenormalization.py
onnion_runtime/isinf.py
onnion_runtime/isnan.py
onnion_runtime/leakyrelu.py
onnion_runtime/less.py
onnion_runtime/lessorequal.py
onnion_runtime/log.py
onnion_runtime/logsoftmax.py
onnion_runtime/loop.py
onnion_runtime/matmul.py
onnion_runtime/matmulinteger.py
onnion_runtime/max.py
onnion_runtime/mean.py
onnion_runtime/min.py
onnion_runtime/mod.py
onnion_runtime/mul.py
onnion_runtime/neg.py
onnion_runtime/negativeloglikelihoodloss.py
onnion_runtime/nonmaxsuppression.py
onnion_runtime/nonzero.py
onnion_rt-0.8.0.dist-info/LICENSE
onnion_rt-0.8.0.dist-info/METADATA
onnion_rt-0.8.0.dist-info/WHEEL
onnion_rt-0.8.0.dist-info/RECORD
