Metadata-Version: 2.1
Name: onnion-rt
Version: 0.8.0
Summary: run onnx with only numpy
Home-page: https://github.com/Idein/onnion/tree/master/runtime
License: Apache-2.0
Keywords: onnx
Author: Idein Inc.
Requires-Python: >=3.7,<4.0
Classifier: License :: OSI Approved :: Apache Software License
Classifier: Programming Language :: Python :: 3
Classifier: Programming Language :: Python :: 3.7
Classifier: Programming Language :: Python :: 3.8
Classifier: Programming Language :: Python :: 3.9
Classifier: Programming Language :: Python :: 3.10
Classifier: Programming Language :: Python :: 3.11
Requires-Dist: numpy (>=1.19.5,<1.21.5) ; python_version < "3.8"
Requires-Dist: numpy (>=1.19.5,<2.0.0) ; python_version >= "3.8"
Project-URL: Repository, https://github.com/Idein/onnion/tree/master/runtime
